toon_to_pdf/__init__.py
toon_to_pdf/converter.py
toon_to_pdf-0.1.0.dist-info/licenses/LICENSE
toon_to_pdf-0.1.0.dist-info/METADATA
toon_to_pdf-0.1.0.dist-info/WHEEL
toon_to_pdf-0.1.0.dist-info/top_level.txt
toon_to_pdf-0.1.0.dist-info/RECORD
