Metadata-Version: 2.4
Name: toon-to-pdf
Version: 0.1.0
Summary: A lightweight library to convert TOON format files to PDF using pdfme
Author-email: Your Name <your.email@example.com>
License: MIT
Project-URL: Homepage, https://github.com/yourusername/toon-to-pdf
Project-URL: Documentation, https://github.com/yourusername/toon-to-pdf#readme
Project-URL: Repository, https://github.com/yourusername/toon-to-pdf
Keywords: toon,pdf,converter,pdfme
Classifier: Development Status :: 3 - Alpha
Classifier: Intended Audience :: Developers
Classifier: License :: OSI Approved :: MIT License
Classifier: Programming Language :: Python :: 3
Classifier: Programming Language :: Python :: 3.8
Classifier: Programming Language :: Python :: 3.9
Classifier: Programming Language :: Python :: 3.10
Classifier: Programming Language :: Python :: 3.11
Requires-Python: >=3.8
License-File: LICENSE
Requires-Dist: pdfme>=0.1.0
Provides-Extra: dev
Requires-Dist: pytest>=7.0.0; extra == "dev"
Requires-Dist: black>=22.0.0; extra == "dev"
Requires-Dist: flake8>=5.0.0; extra == "dev"
Dynamic: license-file
